osprem/__init__.py
osprem-0.0.0.dist-info/METADATA
osprem-0.0.0.dist-info/WHEEL
osprem-0.0.0.dist-info/top_level.txt
osprem-0.0.0.dist-info/RECORD
