Metadata-Version: 2.1
Name: osprem
Version: 0.0.0
Summary: Coming soon
Author-email: Juan Sanchez <info@devsim.com>
